[{"id":800001,"typeId":8,"iconUrl":"{base}/tops/800001.png","sex":1,"resourceId":"clothes_tops.2","price":0,"currency":0,"quantity":0,"clanLevel":0,"isNew":0},{"id":800002,"typeId":8,"iconUrl":"{base}/tops/800002.png","sex":1,"resourceId":"clothes_tops.3","price":0,"currency":0,"quantity":0,"clanLevel":0,"isNew":0},{"id":800003,"typeId":8,"iconUrl":"{base}/tops/800003.png","sex":1,"resourceId":"clothes_tops.4","price":0,"currency":0,"quantity":0,"clanLevel":0,"isNew":0},{"id":800004,"typeId":8,"iconUrl":"{base}/tops/800004.png","sex":2,"resourceId":"clothes_tops.2","price":0,"currency":0,"quantity":0,"clanLevel":0,"isNew":0},{"id":800005,"typeId":8,"iconUrl":"{base}/tops/800005.png","sex":2,"resourceId":"clothes_tops.3","price":0,"currency":0,"quantity":0,"clanLevel":0,"isNew":0},{"id":800006,"typeId":8,"iconUrl":"{base}/tops/800006.png","sex":2,"resourceId":"clothes_tops.4","price":0,"currency":0,"quantity":0,"clanLevel":0,"isNew":0},{"id":800007,"typeId":8,"iconUrl":"{base}/tops/800007.png","sex":2,"resourceId":"clothes_tops.12","price":6000,"currency":2,"quantity":0,"clanLevel":0,"isNew":0},{"id":800008,"typeId":8,"iconUrl":"{base}/tops/800008.png","sex":2,"resourceId":"clothes_tops.11","price":6000,"currency":2,"quantity":0,"clanLevel":0,"isNew":1},{"id":800009,"typeId":8,"iconUrl":"{base}/tops/800009.png","sex":2,"resourceId":"clothes_tops.10","price":6000,"currency":2,"quantity":0,"clanLevel":0,"isNew":1},{"id":800010,"typeId":8,"iconUrl":"{base}/tops/800010.png","sex":2,"resourceId":"clothes_tops.9","price":6000,"currency":2,"quantity":0,"clanLevel":0,"isNew":1},{"id":800011,"typeId":8,"iconUrl":"{base}/tops/800011.png","sex":2,"resourceId":"clothes_tops.8","price":6000,"currency":2,"quantity":0,"clanLevel":0,"isNew":1},{"id":800012,"typeId":8,"iconUrl":"{base}/tops/800012.png","sex":2,"resourceId":"clothes_tops.7","price":100,"currency":1,"quantity":0,"clanLevel":0,"isNew":1},{"id":800013,"typeId":8,"iconUrl":"{base}/tops/800013.png","sex":2,"resourceId":"clothes_tops.6","price":100,"currency":1,"quantity":0,"clanLevel":0,"isNew":1},{"id":800014,"typeId":8,"iconUrl":"{base}/tops/800014.png","sex":2,"resourceId":"clothes_tops.5","price":100,"currency":1,"quantity":0,"clanLevel":0,"isNew":1},{"id":800015,"typeId":8,"iconUrl":"{base}/tops/800015.png","sex":1,"resourceId":"clothes_tops.12","price":6000,"currency":2,"quantity":0,"clanLevel":0,"isNew":1},{"id":800016,"typeId":8,"iconUrl":"{base}/tops/800016.png","sex":1,"resourceId":"clothes_tops.11","price":6000,"currency":2,"quantity":0,"clanLevel":0,"isNew":1},{"id":800017,"typeId":8,"iconUrl":"{base}/tops/800017.png","sex":1,"resourceId":"clothes_tops.10","price":6000,"currency":2,"quantity":0,"clanLevel":0,"isNew":1},{"id":800018,"typeId":8,"iconUrl":"{base}/tops/800018.png","sex":1,"resourceId":"clothes_tops.9","price":6000,"currency":2,"quantity":0,"clanLevel":0,"isNew":1},{"id":800019,"typeId":8,"iconUrl":"{base}/tops/800019.png","sex":1,"resourceId":"clothes_tops.8","price":6000,"currency":2,"quantity":0,"clanLevel":0,"isNew":1},{"id":800020,"typeId":8,"iconUrl":"{base}/tops/800020.png","sex":1,"resourceId":"clothes_tops.7","price":100,"currency":1,"quantity":0,"clanLevel":0,"isNew":1},{"id":800021,"typeId":8,"iconUrl":"{base}/tops/800021.png","sex":1,"resourceId":"clothes_tops.6","price":100,"currency":1,"quantity":0,"clanLevel":0,"isNew":1},{"id":800022,"typeId":8,"iconUrl":"{base}/tops/800022.png","sex":1,"resourceId":"clothes_tops.5","price":100,"currency":1,"quantity":0,"clanLevel":0,"isNew":1},{"id":800023,"typeId":8,"iconUrl":"{base}/tops/800023.png","sex":1,"resourceId":"clothes_tops.17","price":100,"currency":1,"quantity":0,"clanLevel":0,"isNew":1},{"id":800024,"typeId":8,"iconUrl":"{base}/tops/800024.png","sex":1,"resourceId":"clothes_tops.16","price":100,"currency":1,"quantity":0,"clanLevel":0,"isNew":1},{"id":800025,"typeId":8,"iconUrl":"{base}/tops/800025.png","sex":1,"resourceId":"clothes_tops.15","price":100,"currency":1,"quantity":0,"clanLevel":0,"isNew":1},{"id":800026,"typeId":8,"iconUrl":"{base}/tops/800026.png","sex":1,"resourceId":"clothes_tops.14","price":100,"currency":1,"quantity":0,"clanLevel":0,"isNew":1},{"id":800027,"typeId":8,"iconUrl":"{base}/tops/800027.png","sex":2,"resourceId":"clothes_tops.13","price":0,"currency":0,"quantity":0,"clanLevel":0,"isNew":1},{"id":800028,"typeId":8,"iconUrl":"{base}/tops/800028.png","sex":1,"resourceId":"clothes_tops.13","price":0,"currency":0,"quantity":0,"clanLevel":0,"isNew":1},{"id":800029,"typeId":8,"iconUrl":"{base}/tops/800029.png","sex":1,"resourceId":"clothes_tops.18","price":100,"currency":1,"quantity":0,"clanLevel":0,"isNew":1},{"id":800030,"typeId":8,"iconUrl":"{base}/tops/800030.png","sex":1,"resourceId":"clothes_tops.20","price":100,"currency":1,"quantity":0,"clanLevel":0,"isNew":1},{"id":800031,"typeId":8,"iconUrl":"{base}/tops/800031.png","sex":1,"resourceId":"clothes_tops.19","price":100,"currency":1,"quantity":0,"clanLevel":0,"isNew":1},{"id":800032,"typeId":8,"iconUrl":"{base}/tops/800032.png","sex":2,"resourceId":"clothes_tops.19","price":120,"currency":1,"quantity":0,"clanLevel":0,"isNew":1},{"id":800033,"typeId":8,"iconUrl":"{base}/tops/800033.png","sex":2,"resourceId":"clothes_tops.18","price":120,"currency":1,"quantity":0,"clanLevel":0,"isNew":0},{"id":800034,"typeId":8,"iconUrl":"{base}/tops/800034.png","sex":2,"resourceId":"clothes_tops.17","price":100,"currency":1,"quantity":0,"clanLevel":0,"isNew":1},{"id":800035,"typeId":8,"iconUrl":"{base}/tops/800035.png","sex":2,"resourceId":"clothes_tops.16","price":100,"currency":1,"quantity":0,"clanLevel":0,"isNew":1},{"id":800036,"typeId":8,"iconUrl":"{base}/tops/800036.png","sex":2,"resourceId":"clothes_tops.15","price":100,"currency":1,"quantity":0,"clanLevel":0,"isNew":1},{"id":800037,"typeId":8,"iconUrl":"{base}/tops/800037.png","sex":2,"resourceId":"clothes_tops.14","price":100,"currency":1,"quantity":0,"clanLevel":0,"isNew":1},{"id":800038,"typeId":8,"iconUrl":"{base}/tops/800038.png","sex":0,"resourceId":"clothes_tops.3004","price":9000,"currency":1,"quantity":0,"clanLevel":9,"isNew":1},{"id":800039,"typeId":8,"iconUrl":"{base}/tops/800039.png","sex":0,"resourceId":"clothes_tops.3003","price":7200,"currency":1,"quantity":0,"clanLevel":5,"isNew":1},{"id":800040,"typeId":8,"iconUrl":"{base}/tops/800040.png","sex":0,"resourceId":"clothes_tops.3002","price":7200,"currency":1,"quantity":0,"clanLevel":2,"isNew":1},{"id":800041,"typeId":8,"iconUrl":"{base}/tops/800041.png","sex":0,"resourceId":"clothes_tops.3001","price":6000,"currency":1,"quantity":0,"clanLevel":1,"isNew":1},{"id":800042,"typeId":8,"iconUrl":"{base}/tops/800042.png","sex":0,"resourceId":"clothes_tops.33","price":8000,"currency":2,"quantity":0,"clanLevel":0,"isNew":1},{"id":800043,"typeId":8,"iconUrl":"{base}/tops/800043.png","sex":0,"resourceId":"clothes_tops.32","price":8000,"currency":2,"quantity":0,"clanLevel":0,"isNew":1},{"id":800044,"typeId":8,"iconUrl":"{base}/tops/800044.png","sex":0,"resourceId":"clothes_tops.31","price":8000,"currency":2,"quantity":0,"clanLevel":0,"isNew":1},{"id":800045,"typeId":8,"iconUrl":"{base}/tops/800045.png","sex":0,"resourceId":"clothes_tops.30","price":8000,"currency":2,"quantity":0,"clanLevel":0,"isNew":1},{"id":800046,"typeId":8,"iconUrl":"{base}/tops/800046.png","sex":0,"resourceId":"clothes_tops.29","price":8000,"currency":2,"quantity":0,"clanLevel":0,"isNew":1},{"id":800047,"typeId":8,"iconUrl":"{base}/tops/800047.png","sex":0,"resourceId":"clothes_tops.28","price":8000,"currency":2,"quantity":0,"clanLevel":0,"isNew":1},{"id":800048,"typeId":8,"iconUrl":"{base}/tops/800048.png","sex":0,"resourceId":"clothes_tops.27","price":8000,"currency":2,"quantity":0,"clanLevel":0,"isNew":1},{"id":800049,"typeId":8,"iconUrl":"{base}/tops/800049.png","sex":0,"resourceId":"clothes_tops.26","price":8000,"currency":2,"quantity":0,"clanLevel":0,"isNew":1},{"id":800050,"typeId":8,"iconUrl":"{base}/tops/800050.png","sex":0,"resourceId":"clothes_tops.25","price":8000,"currency":2,"quantity":0,"clanLevel":0,"isNew":1},{"id":800051,"typeId":8,"iconUrl":"{base}/tops/800051.png","sex":0,"resourceId":"clothes_tops.24","price":8000,"currency":2,"quantity":0,"clanLevel":0,"isNew":1},{"id":800052,"typeId":8,"iconUrl":"{base}/tops/800052.png","sex":0,"resourceId":"clothes_tops.23","price":8000,"currency":2,"quantity":0,"clanLevel":0,"isNew":1},{"id":800053,"typeId":8,"iconUrl":"{base}/tops/800053.png","sex":0,"resourceId":"clothes_tops.22","price":8000,"currency":2,"quantity":0,"clanLevel":0,"isNew":1},{"id":800054,"typeId":8,"iconUrl":"{base}/tops/800054.png","sex":0,"resourceId":"clothes_tops.21","price":8000,"currency":2,"quantity":0,"clanLevel":0,"isNew":1},{"id":800055,"typeId":8,"iconUrl":"{base}/tops/800055.png","sex":0,"resourceId":"clothes_tops.34","price":9999,"currency":1,"quantity":0,"clanLevel":0,"isNew":0},{"id":800056,"typeId":8,"iconUrl":"{base}/tops/800056.png","sex":0,"resourceId":"clothes_tops.49","price":6000,"currency":2,"quantity":0,"clanLevel":0,"isNew":1},{"id":800057,"typeId":8,"iconUrl":"{base}/tops/800057.png","sex":0,"resourceId":"clothes_tops.48","price":6000,"currency":2,"quantity":0,"clanLevel":0,"isNew":1},{"id":800058,"typeId":8,"iconUrl":"{base}/tops/800058.png","sex":0,"resourceId":"clothes_tops.47","price":6000,"currency":2,"quantity":0,"clanLevel":0,"isNew":1},{"id":800059,"typeId":8,"iconUrl":"{base}/tops/800059.png","sex":0,"resourceId":"clothes_tops.46","price":6000,"currency":2,"quantity":0,"clanLevel":0,"isNew":1},{"id":800060,"typeId":8,"iconUrl":"{base}/tops/800060.png","sex":0,"resourceId":"clothes_tops.45","price":6000,"currency":2,"quantity":0,"clanLevel":0,"isNew":1},{"id":800061,"typeId":8,"iconUrl":"{base}/tops/800061.png","sex":0,"resourceId":"clothes_tops.44","price":6000,"currency":2,"quantity":0,"clanLevel":0,"isNew":1},{"id":800062,"typeId":8,"iconUrl":"{base}/tops/800062.png","sex":0,"resourceId":"clothes_tops.43","price":6000,"currency":2,"quantity":0,"clanLevel":0,"isNew":1},{"id":800063,"typeId":8,"iconUrl":"{base}/tops/800063.png","sex":0,"resourceId":"clothes_tops.42","price":6000,"currency":2,"quantity":0,"clanLevel":0,"isNew":1},{"id":800064,"typeId":8,"iconUrl":"{base}/tops/800064.png","sex":0,"resourceId":"clothes_tops.41","price":6000,"currency":2,"quantity":0,"clanLevel":0,"isNew":1},{"id":800065,"typeId":8,"iconUrl":"{base}/tops/800065.png","sex":0,"resourceId":"clothes_tops.40","price":6000,"currency":2,"quantity":0,"clanLevel":0,"isNew":1},{"id":800066,"typeId":8,"iconUrl":"{base}/tops/800066.png","sex":0,"resourceId":"clothes_tops.39","price":6000,"currency":2,"quantity":0,"clanLevel":0,"isNew":1},{"id":800067,"typeId":8,"iconUrl":"{base}/tops/800067.png","sex":0,"resourceId":"clothes_tops.38","price":6000,"currency":2,"quantity":0,"clanLevel":0,"isNew":1},{"id":800068,"typeId":8,"iconUrl":"{base}/tops/800068.png","sex":2,"resourceId":"clothes_tops.70","price":100,"currency":1,"quantity":0,"clanLevel":0,"isNew":1},{"id":800069,"typeId":8,"iconUrl":"{base}/tops/800069.png","sex":1,"resourceId":"clothes_tops.62","price":6000,"currency":2,"quantity":0,"clanLevel":0,"isNew":1},{"id":800070,"typeId":8,"iconUrl":"{base}/tops/800070.png","sex":2,"resourceId":"clothes_tops.61","price":6000,"currency":2,"quantity":0,"clanLevel":0,"isNew":1},{"id":800071,"typeId":8,"iconUrl":"{base}/tops/800071.png","sex":1,"resourceId":"clothes_tops.61","price":100,"currency":1,"quantity":0,"clanLevel":0,"isNew":1},{"id":800072,"typeId":8,"iconUrl":"{base}/tops/800072.png","sex":2,"resourceId":"clothes_tops.63","price":100,"currency":1,"quantity":0,"clanLevel":0,"isNew":1},{"id":800073,"typeId":8,"iconUrl":"{base}/tops/800073.png","sex":1,"resourceId":"clothes_tops.63","price":6000,"currency":2,"quantity":0,"clanLevel":0,"isNew":1},{"id":800074,"typeId":8,"iconUrl":"{base}/tops/800074.png","sex":2,"resourceId":"clothes_tops.62","price":6000,"currency":2,"quantity":0,"clanLevel":0,"isNew":1},{"id":800075,"typeId":8,"iconUrl":"{base}/tops/800075.png","sex":1,"resourceId":"clothes_tops.59","price":100,"currency":1,"quantity":0,"clanLevel":0,"isNew":1},{"id":800076,"typeId":8,"iconUrl":"{base}/tops/800076.png","sex":0,"resourceId":"clothes_tops.58","price":6000,"currency":2,"quantity":0,"clanLevel":0,"isNew":1},{"id":800077,"typeId":8,"iconUrl":"{base}/tops/800077.png","sex":0,"resourceId":"clothes_tops.57","price":6000,"currency":2,"quantity":0,"clanLevel":0,"isNew":1},{"id":800078,"typeId":8,"iconUrl":"{base}/tops/800078.png","sex":0,"resourceId":"clothes_tops.56","price":6000,"currency":2,"quantity":0,"clanLevel":0,"isNew":1},{"id":800079,"typeId":8,"iconUrl":"{base}/tops/800079.png","sex":2,"resourceId":"clothes_tops.55","price":6000,"currency":2,"quantity":0,"clanLevel":0,"isNew":1},{"id":800080,"typeId":8,"iconUrl":"{base}/tops/800080.png","sex":1,"resourceId":"clothes_tops.55","price":6000,"currency":2,"quantity":0,"clanLevel":0,"isNew":1},{"id":800081,"typeId":8,"iconUrl":"{base}/tops/800081.png","sex":0,"resourceId":"clothes_tops.54","price":6000,"currency":2,"quantity":0,"clanLevel":0,"isNew":1},{"id":800082,"typeId":8,"iconUrl":"{base}/tops/800082.png","sex":2,"resourceId":"clothes_tops.53","price":6000,"currency":2,"quantity":0,"clanLevel":0,"isNew":1},{"id":800083,"typeId":8,"iconUrl":"{base}/tops/800083.png","sex":1,"resourceId":"clothes_tops.53","price":6000,"currency":2,"quantity":0,"clanLevel":0,"isNew":1},{"id":800084,"typeId":8,"iconUrl":"{base}/tops/800084.png","sex":0,"resourceId":"clothes_tops.60","price":100,"currency":1,"quantity":0,"clanLevel":0,"isNew":1},{"id":800085,"typeId":8,"iconUrl":"{base}/tops/800085.png","sex":2,"resourceId":"clothes_tops.52","price":100,"currency":1,"quantity":0,"clanLevel":0,"isNew":1},{"id":800086,"typeId":8,"iconUrl":"{base}/tops/800086.png","sex":1,"resourceId":"clothes_tops.52","price":100,"currency":1,"quantity":0,"clanLevel":0,"isNew":1},{"id":800087,"typeId":8,"iconUrl":"{base}/tops/800087.png","sex":2,"resourceId":"clothes_tops.64","price":100,"currency":1,"quantity":0,"clanLevel":0,"isNew":1},{"id":800088,"typeId":8,"iconUrl":"{base}/tops/800088.png","sex":1,"resourceId":"clothes_tops.66","price":6000,"currency":2,"quantity":0,"clanLevel":0,"isNew":1},{"id":800089,"typeId":8,"iconUrl":"{base}/tops/800089.png","sex":2,"resourceId":"clothes_tops.66","price":6000,"currency":2,"quantity":0,"clanLevel":0,"isNew":1},{"id":800090,"typeId":8,"iconUrl":"{base}/tops/800090.png","sex":2,"resourceId":"clothes_tops.37","price":10000,"currency":2,"quantity":0,"clanLevel":0,"isNew":1},{"id":800091,"typeId":8,"iconUrl":"{base}/tops/800091.png","sex":2,"resourceId":"clothes_tops.65","price":9999,"currency":1,"quantity":0,"clanLevel":0,"isNew":1},{"id":800092,"typeId":8,"iconUrl":"{base}/tops/800092.png","sex":1,"resourceId":"clothes_tops.65","price":9999,"currency":1,"quantity":0,"clanLevel":0,"isNew":1},{"id":800093,"typeId":8,"iconUrl":"{base}/tops/800093.png","sex":1,"resourceId":"clothes_tops.64","price":6000,"currency":2,"quantity":0,"clanLevel":0,"isNew":1},{"id":800094,"typeId":8,"iconUrl":"{base}/tops/800094.png","sex":1,"resourceId":"clothes_tops.68","price":100,"currency":1,"quantity":0,"clanLevel":0,"isNew":0},{"id":800095,"typeId":8,"iconUrl":"{base}/tops/800095.png","sex":2,"resourceId":"clothes_tops.68","price":100,"currency":1,"quantity":0,"clanLevel":0,"isNew":0},{"id":800096,"typeId":8,"iconUrl":"{base}/tops/800096.png","sex":2,"resourceId":"clothes_tops.69","price":80,"currency":1,"quantity":0,"clanLevel":0,"isNew":0},{"id":800097,"typeId":8,"iconUrl":"{base}/tops/800097.png","sex":1,"resourceId":"clothes_tops.69","price":80,"currency":1,"quantity":0,"clanLevel":0,"isNew":1},{"id":800098,"typeId":8,"iconUrl":"{base}/tops/800098.png","sex":1,"resourceId":"clothes_tops.70","price":100,"currency":1,"quantity":0,"clanLevel":0,"isNew":1},{"id":800099,"typeId":8,"iconUrl":"{base}/tops/800099.png","sex":2,"resourceId":"clothes_tops.72","price":120,"currency":1,"quantity":0,"clanLevel":0,"isNew":1},{"id":800100,"typeId":8,"iconUrl":"{base}/tops/800100.png","sex":1,"resourceId":"clothes_tops.72","price":100,"currency":1,"quantity":0,"clanLevel":0,"isNew":1},{"id":800101,"typeId":8,"iconUrl":"{base}/tops/800101.png","sex":1,"resourceId":"clothes_tops.73","price":160,"currency":1,"quantity":0,"clanLevel":0,"isNew":0},{"id":800102,"typeId":8,"iconUrl":"{base}/tops/800102.png","sex":1,"resourceId":"clothes_tops.74","price":6000,"currency":2,"quantity":0,"clanLevel":0,"isNew":1},{"id":800103,"typeId":8,"iconUrl":"{base}/tops/800103.png","sex":2,"resourceId":"clothes_tops.73","price":6000,"currency":2,"quantity":0,"clanLevel":0,"isNew":1},{"id":800104,"typeId":8,"iconUrl":"{base}/tops/800104.png","sex":1,"resourceId":"clothes_tops.75","price":6000,"currency":2,"quantity":0,"clanLevel":0,"isNew":1},{"id":800105,"typeId":8,"iconUrl":"{base}/tops/800105.png","sex":2,"resourceId":"clothes_tops.74","price":6000,"currency":2,"quantity":0,"clanLevel":0,"isNew":1},{"id":800106,"typeId":8,"iconUrl":"{base}/tops/800106.png","sex":1,"resourceId":"clothes_tops.76","price":100,"currency":1,"quantity":0,"clanLevel":0,"isNew":1},{"id":800107,"typeId":8,"iconUrl":"{base}/tops/800107.png","sex":2,"resourceId":"clothes_tops.75","price":100,"currency":1,"quantity":0,"clanLevel":0,"isNew":1},{"id":800108,"typeId":8,"iconUrl":"{base}/tops/800108.png","sex":1,"resourceId":"clothes_tops.77","price":100,"currency":1,"quantity":0,"clanLevel":0,"isNew":1},{"id":800109,"typeId":8,"iconUrl":"{base}/tops/800109.png","sex":2,"resourceId":"clothes_tops.76","price":100,"currency":1,"quantity":0,"clanLevel":0,"isNew":1},{"id":800110,"typeId":8,"iconUrl":"{base}/tops/800110.png","sex":1,"resourceId":"clothes_tops.78","price":100,"currency":1,"quantity":0,"clanLevel":0,"isNew":1},{"id":800111,"typeId":8,"iconUrl":"{base}/tops/800111.png","sex":2,"resourceId":"clothes_tops.77","price":100,"currency":1,"quantity":0,"clanLevel":0,"isNew":1},{"id":800112,"typeId":8,"iconUrl":"{base}/tops/800112.png","sex":0,"resourceId":"clothes_tops.79","price":100,"currency":1,"quantity":0,"clanLevel":0,"isNew":1},{"id":800113,"typeId":8,"iconUrl":"{base}/tops/800113.png","sex":2,"resourceId":"clothes_tops.81","price":0,"currency":1,"quantity":0,"clanLevel":0,"isNew":1},{"id":800114,"typeId":8,"iconUrl":"{base}/tops/800114.png","sex":1,"resourceId":"clothes_tops.82","price":0,"currency":1,"quantity":0,"clanLevel":0,"isNew":1},{"id":800115,"typeId":8,"iconUrl":"{base}/tops/800115.png","sex":2,"resourceId":"clothes_tops.71","price":0,"currency":1,"quantity":0,"clanLevel":0,"isNew":1},{"id":800116,"typeId":8,"iconUrl":"{base}/tops/800116.png","sex":1,"resourceId":"clothes_tops.71","price":0,"currency":1,"quantity":0,"clanLevel":0,"isNew":1},{"id":800117,"typeId":8,"iconUrl":"{base}/tops/800117.png","sex":2,"resourceId":"clothes_tops.80","price":0,"currency":2,"quantity":0,"clanLevel":0,"isNew":1},{"id":800118,"typeId":8,"iconUrl":"{base}/tops/800118.png","sex":2,"resourceId":"clothes_tops.78","price":0,"currency":2,"quantity":0,"clanLevel":0,"isNew":1},{"id":800119,"typeId":8,"iconUrl":"{base}/tops/800119.png","sex":1,"resourceId":"clothes_tops.81","price":0,"currency":2,"quantity":0,"clanLevel":0,"isNew":1},{"id":800120,"typeId":8,"iconUrl":"{base}/tops/800120.png","sex":1,"resourceId":"clothes_tops.80","price":0,"currency":2,"quantity":0,"clanLevel":0,"isNew":1},{"id":800121,"typeId":8,"iconUrl":"{base}/tops/800121.png","sex":1,"resourceId":"clothes_tops.87","price":6000,"currency":2,"quantity":0,"clanLevel":0,"isNew":1},{"id":800122,"typeId":8,"iconUrl":"{base}/tops/800122.png","sex":2,"resourceId":"clothes_tops.87","price":6000,"currency":2,"quantity":0,"clanLevel":0,"isNew":1},{"id":800123,"typeId":8,"iconUrl":"{base}/tops/800123.png","sex":1,"resourceId":"clothes_tops.86","price":6000,"currency":2,"quantity":0,"clanLevel":0,"isNew":1},{"id":800124,"typeId":8,"iconUrl":"{base}/tops/800124.png","sex":2,"resourceId":"clothes_tops.86","price":6000,"currency":2,"quantity":0,"clanLevel":0,"isNew":1},{"id":800125,"typeId":8,"iconUrl":"{base}/tops/800125.png","sex":1,"resourceId":"clothes_tops.84","price":100,"currency":1,"quantity":0,"clanLevel":0,"isNew":1},{"id":800126,"typeId":8,"iconUrl":"{base}/tops/800126.png","sex":2,"resourceId":"clothes_tops.84","price":100,"currency":1,"quantity":0,"clanLevel":0,"isNew":1},{"id":800127,"typeId":8,"iconUrl":"{base}/tops/800127.png","sex":1,"resourceId":"clothes_tops.85","price":100,"currency":1,"quantity":0,"clanLevel":0,"isNew":1},{"id":800128,"typeId":8,"iconUrl":"{base}/tops/800128.png","sex":2,"resourceId":"clothes_tops.83","price":100,"currency":1,"quantity":0,"clanLevel":0,"isNew":1},{"id":800129,"typeId":8,"iconUrl":"{base}/tops/800129.png","sex":1,"resourceId":"clothes_tops.83","price":160,"currency":1,"quantity":0,"clanLevel":0,"isNew":1},{"id":800130,"typeId":8,"iconUrl":"{base}/tops/800130.png","sex":2,"resourceId":"clothes_tops.82","price":160,"currency":1,"quantity":0,"clanLevel":0,"isNew":1},{"id":800131,"typeId":8,"iconUrl":"{base}/tops/800131.png","sex":1,"resourceId":"clothes_tops.88","price":100,"currency":1,"quantity":0,"clanLevel":0,"isNew":1},{"id":800132,"typeId":8,"iconUrl":"{base}/tops/800132.png","sex":2,"resourceId":"clothes_tops.85","price":100,"currency":1,"quantity":0,"clanLevel":0,"isNew":1},{"id":800133,"typeId":8,"iconUrl":"{base}/tops/800133.png","sex":1,"resourceId":"clothes_tops.89","price":0,"currency":1,"quantity":0,"clanLevel":0,"isNew":1},{"id":800134,"typeId":8,"iconUrl":"{base}/tops/800134.png","sex":2,"resourceId":"clothes_tops.88","price":0,"currency":1,"quantity":0,"clanLevel":0,"isNew":1},{"id":800135,"typeId":8,"iconUrl":"{base}/tops/800135.png","sex":1,"resourceId":"clothes_tops.90","price":0,"currency":1,"quantity":0,"clanLevel":0,"isNew":1},{"id":800136,"typeId":8,"iconUrl":"{base}/tops/800136.png","sex":2,"resourceId":"clothes_tops.89","price":0,"currency":1,"quantity":0,"clanLevel":0,"isNew":1},{"id":800137,"typeId":8,"iconUrl":"{base}/tops/800137.png","sex":2,"resourceId":"clothes_tops.90","price":0,"currency":1,"quantity":0,"clanLevel":0,"isNew":1},{"id":800138,"typeId":8,"iconUrl":"{base}/tops/800138.png","sex":1,"resourceId":"clothes_tops.91","price":0,"currency":1,"quantity":0,"clanLevel":0,"isNew":1},{"id":800139,"typeId":8,"iconUrl":"{base}/tops/800139.png","sex":1,"resourceId":"clothes_tops.95","price":160,"currency":1,"quantity":0,"clanLevel":0,"isNew":1},{"id":800140,"typeId":8,"iconUrl":"{base}/tops/800140.png","sex":2,"resourceId":"clothes_tops.94","price":160,"currency":1,"quantity":0,"clanLevel":0,"isNew":1},{"id":800141,"typeId":8,"iconUrl":"{base}/tops/800141.png","sex":1,"resourceId":"clothes_tops.96","price":160,"currency":1,"quantity":0,"clanLevel":0,"isNew":1},{"id":800142,"typeId":8,"iconUrl":"{base}/tops/800142.png","sex":2,"resourceId":"clothes_tops.95","price":160,"currency":1,"quantity":0,"clanLevel":0,"isNew":1},{"id":800143,"typeId":8,"iconUrl":"{base}/tops/800143.png","sex":1,"resourceId":"clothes_tops.93","price":0,"currency":1,"quantity":0,"clanLevel":0,"isNew":1},{"id":800144,"typeId":8,"iconUrl":"{base}/tops/800144.png","sex":2,"resourceId":"clothes_tops.92","price":0,"currency":1,"quantity":0,"clanLevel":0,"isNew":1},{"id":800145,"typeId":8,"iconUrl":"{base}/tops/800145.png","sex":1,"resourceId":"clothes_tops.92","price":0,"currency":1,"quantity":0,"clanLevel":0,"isNew":1},{"id":800146,"typeId":8,"iconUrl":"{base}/tops/800146.png","sex":2,"resourceId":"clothes_tops.91","price":0,"currency":1,"quantity":0,"clanLevel":0,"isNew":1},{"id":800147,"typeId":8,"iconUrl":"{base}/tops/800147.png","sex":1,"resourceId":"clothes_tops.94","price":9000,"currency":2,"quantity":0,"clanLevel":0,"isNew":1},{"id":800148,"typeId":8,"iconUrl":"{base}/tops/800148.png","sex":2,"resourceId":"clothes_tops.93","price":9000,"currency":2,"quantity":0,"clanLevel":0,"isNew":1},{"id":800149,"typeId":8,"iconUrl":"{base}/tops/800149.png","sex":1,"resourceId":"clothes_tops.97","price":80,"currency":1,"quantity":0,"clanLevel":0,"isNew":1},{"id":800150,"typeId":8,"iconUrl":"{base}/tops/800150.png","sex":2,"resourceId":"clothes_tops.96","price":80,"currency":1,"quantity":0,"clanLevel":0,"isNew":1},{"id":800151,"typeId":8,"iconUrl":"{base}/tops/800151.png","sex":2,"resourceId":"clothes_tops.98","price":80,"currency":1,"quantity":0,"clanLevel":0,"isNew":1},{"id":800152,"typeId":8,"iconUrl":"{base}/tops/800152.png","sex":1,"resourceId":"clothes_tops.99","price":80,"currency":1,"quantity":0,"clanLevel":0,"isNew":1},{"id":800153,"typeId":8,"iconUrl":"{base}/tops/800153.png","sex":1,"resourceId":"clothes_tops.98","price":100,"currency":1,"quantity":0,"clanLevel":0,"isNew":1},{"id":800154,"typeId":8,"iconUrl":"{base}/tops/800154.png","sex":2,"resourceId":"clothes_tops.97","price":100,"currency":1,"quantity":0,"clanLevel":0,"isNew":1},{"id":800155,"typeId":8,"iconUrl":"{base}/tops/800155.png","sex":2,"resourceId":"clothes_tops.100","price":160,"currency":1,"quantity":0,"clanLevel":0,"isNew":1},{"id":800156,"typeId":8,"iconUrl":"{base}/tops/800156.png","sex":2,"resourceId":"clothes_tops.99","price":160,"currency":1,"quantity":0,"clanLevel":0,"isNew":1},{"id":800157,"typeId":8,"iconUrl":"{base}/tops/800157.png","sex":1,"resourceId":"clothes_tops.101","price":80,"currency":1,"quantity":0,"clanLevel":0,"isNew":1},{"id":800158,"typeId":8,"iconUrl":"{base}/tops/800158.png","sex":1,"resourceId":"clothes_tops.102","price":160,"currency":1,"quantity":0,"clanLevel":0,"isNew":1},{"id":800159,"typeId":8,"iconUrl":"{base}/tops/800159.png","sex":2,"resourceId":"clothes_tops.101","price":160,"currency":1,"quantity":0,"clanLevel":0,"isNew":1},{"id":800160,"typeId":8,"iconUrl":"{base}/tops/800160.png","sex":1,"resourceId":"clothes_tops.103","price":100,"currency":1,"quantity":0,"clanLevel":0,"isNew":1},{"id":800161,"typeId":8,"iconUrl":"{base}/tops/800161.png","sex":2,"resourceId":"clothes_tops.102","price":100,"currency":1,"quantity":0,"clanLevel":0,"isNew":1},{"id":800162,"typeId":8,"iconUrl":"{base}/tops/800162.png","sex":1,"resourceId":"clothes_tops.105","price":160,"currency":1,"quantity":0,"clanLevel":0,"isNew":1},{"id":800163,"typeId":8,"iconUrl":"{base}/tops/800163.png","sex":2,"resourceId":"clothes_tops.104","price":160,"currency":1,"quantity":0,"clanLevel":0,"isNew":1},{"id":800164,"typeId":8,"iconUrl":"{base}/tops/800164.png","sex":1,"resourceId":"clothes_tops.104","price":160,"currency":1,"quantity":0,"clanLevel":0,"isNew":1},{"id":800165,"typeId":8,"iconUrl":"{base}/tops/800165.png","sex":2,"resourceId":"clothes_tops.103","price":160,"currency":1,"quantity":0,"clanLevel":0,"isNew":1},{"id":800166,"typeId":8,"iconUrl":"{base}/tops/800166.png","sex":1,"resourceId":"clothes_tops.106","price":160,"currency":1,"quantity":0,"clanLevel":0,"isNew":1},{"id":800167,"typeId":8,"iconUrl":"{base}/tops/800167.png","sex":2,"resourceId":"clothes_tops.105","price":160,"currency":1,"quantity":0,"clanLevel":0,"isNew":1},{"id":800168,"typeId":8,"iconUrl":"{base}/tops/800168.png","sex":1,"resourceId":"clothes_tops.107","price":160,"currency":1,"quantity":0,"clanLevel":0,"isNew":1},{"id":800169,"typeId":8,"iconUrl":"{base}/tops/800169.png","sex":2,"resourceId":"clothes_tops.106","price":160,"currency":1,"quantity":0,"clanLevel":0,"isNew":1},{"id":800170,"typeId":8,"iconUrl":"{base}/tops/800170.png","sex":1,"resourceId":"clothes_tops.108","price":0,"currency":1,"quantity":0,"clanLevel":0,"isNew":1},{"id":800171,"typeId":8,"iconUrl":"{base}/tops/800171.png","sex":2,"resourceId":"clothes_tops.107","price":1111,"currency":1,"quantity":0,"clanLevel":0,"isNew":1},{"id":800172,"typeId":8,"iconUrl":"{base}/tops/800172.png","sex":1,"resourceId":"clothes_tops.109","price":0,"currency":1,"quantity":0,"clanLevel":0,"isNew":1},{"id":800173,"typeId":8,"iconUrl":"{base}/tops/800173.png","sex":2,"resourceId":"clothes_tops.108","price":0,"currency":1,"quantity":0,"clanLevel":0,"isNew":1},{"id":800174,"typeId":8,"iconUrl":"{base}/tops/800174.png","sex":1,"resourceId":"clothes_tops.110","price":0,"currency":1,"quantity":0,"clanLevel":0,"isNew":1},{"id":800175,"typeId":8,"iconUrl":"{base}/tops/800175.png","sex":2,"resourceId":"clothes_tops.109","price":0,"currency":1,"quantity":0,"clanLevel":0,"isNew":1},{"id":800176,"typeId":8,"iconUrl":"{base}/tops/800176.png","sex":1,"resourceId":"clothes_tops.111","price":0,"currency":1,"quantity":0,"clanLevel":0,"isNew":1},{"id":800177,"typeId":8,"iconUrl":"{base}/tops/800177.png","sex":2,"resourceId":"clothes_tops.110","price":0,"currency":1,"quantity":0,"clanLevel":0,"isNew":1},{"id":800178,"typeId":8,"iconUrl":"{base}/tops/800178.png","sex":1,"resourceId":"clothes_tops.112","price":1111,"currency":1,"quantity":0,"clanLevel":0,"isNew":1},{"id":800179,"typeId":8,"iconUrl":"{base}/tops/800179.png","sex":2,"resourceId":"clothes_tops.111","price":1111,"currency":1,"quantity":0,"clanLevel":0,"isNew":1},{"id":800180,"typeId":8,"iconUrl":"{base}/tops/800180.png","sex":1,"resourceId":"clothes_tops.113","price":0,"currency":1,"quantity":0,"clanLevel":0,"isNew":1}]